aabc/__init__.py
aabc/aabc.py
aabc-0.1.2.post1.dist-info/LICENSE
aabc-0.1.2.post1.dist-info/METADATA
aabc-0.1.2.post1.dist-info/WHEEL
aabc-0.1.2.post1.dist-info/entry_points.txt
aabc-0.1.2.post1.dist-info/top_level.txt
aabc-0.1.2.post1.dist-info/RECORD
