Metadata-Version: 2.1
Name: aabc
Version: 0.1.2.post1
Summary: Tool that uses adb to check if apps on a device are built Android App Bundles
Home-page: https://github.com/traviswhitehead/aabc
Author: Travis Whitehead
Author-email: TravisWhitehead@protonmail.com
License: UNKNOWN
Platform: UNKNOWN
Classifier: Development Status :: 4 - Beta
Classifier: Environment :: Console
Classifier: Programming Language :: Python :: 3
Classifier: License :: OSI Approved :: GNU General Public License v3 or later (GPLv3+)
Classifier: Operating System :: OS Independent
Requires-Python: >=3.6
